LICENSE
README.md
setup.cfg
setup.py
hubotlibs/__init__.py
hubotlibs/version.py
hubotlibs.egg-info/PKG-INFO
hubotlibs.egg-info/SOURCES.txt
hubotlibs.egg-info/dependency_links.txt
hubotlibs.egg-info/requires.txt
hubotlibs.egg-info/top_level.txt
hubotlibs/dar/__init__.py
hubotlibs/dar/load.py
hubotlibs/dar/log.py
hubotlibs/dar/utils/PyroHelpers.py
hubotlibs/dar/utils/__init__.py
hubotlibs/dar/utils/adminHelpers.py
hubotlibs/dar/utils/ai.py
hubotlibs/dar/utils/aiohttp_helper.py
hubotlibs/dar/utils/basic.py
hubotlibs/dar/utils/constants.py
hubotlibs/dar/utils/function.py
hubotlibs/dar/utils/get_id.py
hubotlibs/dar/utils/http.py
hubotlibs/dar/utils/inline.py
hubotlibs/dar/utils/interval.py
hubotlibs/dar/utils/misc.py
hubotlibs/dar/utils/parser.py
hubotlibs/dar/utils/pilter.py
hubotlibs/dar/utils/tools.py
hubotlibs/dar/utils/unpack.py
hubotlibs/dar/utils/utility.py
hubotlibs/dar/utils/db/__init__.py
hubotlibs/dar/utils/db/permit.py