Metadata-Version: 2.1
Name: hubotlibs
Version: 0.1.8
Summary: A Secure and Powerful Python-Telethon Based Library For Ayra Userbot.
Home-page: https://github.com/XhaidarX/hubotlibs
Author: Haidar
Author-email: XhaidarX00@gmail.com
License: GNU AFFERO GENERAL PUBLIC LICENSE (v3)
Project-URL: Bug Tracker, https://github.com/XhaidarX/hubotlibs/issues
Project-URL: Documentation, https://ultroid.tech
Project-URL: Source Code, https://github.com/XhaidarX/hubotlibs
Classifier: Programming Language :: Python :: 3
Classifier: Programming Language :: Python :: 3.8
Classifier: Programming Language :: Python :: 3.9
Classifier: Programming Language :: Python :: 3.10
Classifier: Programming Language :: Python :: 3.11
Classifier: Programming Language :: Python :: 3.12
Classifier: License :: OSI Approved :: GNU General Public License v3 (GPLv3)
Classifier: Operating System :: OS Independent
Requires-Python: >3.7, <3.12
License-File: LICENSE
